jonga.py
jonga-0.0.4.data/data/share/doc/jonga-0.0.4/example1.ipynb
jonga-0.0.4.data/data/share/doc/jonga-0.0.4/example1.py
jonga-0.0.4.data/data/share/doc/jonga-0.0.4/example2.ipynb
jonga-0.0.4.data/data/share/doc/jonga-0.0.4/example2.py
jonga-0.0.4.data/data/share/doc/jonga-0.0.4/example3.ipynb
jonga-0.0.4.data/data/share/doc/jonga-0.0.4/example3.py
jonga-0.0.4.data/data/share/doc/jonga-0.0.4/example4.ipynb
jonga-0.0.4.data/data/share/doc/jonga-0.0.4/example4.py
jonga-0.0.4.data/data/share/doc/jonga-0.0.4/xmpl.py
jonga-0.0.4.dist-info/LICENSE
jonga-0.0.4.dist-info/METADATA
jonga-0.0.4.dist-info/WHEEL
jonga-0.0.4.dist-info/top_level.txt
jonga-0.0.4.dist-info/zip-safe
jonga-0.0.4.dist-info/RECORD
