Metadata-Version: 2.1
Name: jonga
Version: 0.0.4
Summary: Jonga: Python function call graph visualization
Home-page: https://github.com/bwohlberg/jonga
Author: Brendt Wohlberg
Author-email: brendt@ieee.org
License: GPLv2+
Keywords: Function call graph,Module documentation
Platform: Any
Classifier: Development Status :: 4 - Beta
Classifier: Intended Audience :: Developers
Classifier: License :: OSI Approved :: GNU General Public License v2 or later (GPLv2+)
Classifier: Operating System :: OS Independent
Classifier: Programming Language :: Python :: 3.3
Classifier: Programming Language :: Python :: 3.4
Classifier: Programming Language :: Python :: 3.5
Classifier: Programming Language :: Python :: 3.6
Classifier: Topic :: Utilities
Classifier: Topic :: Software Development :: Documentation
Requires-Dist: pygraphviz
